modelcontextprotocol/__init__.py
modelcontextprotocol/server.py
shared/__init__.py
shared/antom_client.py
shared/service_base.py
shared/payment/__init__.py
shared/payment/request/__init__.py
shared/payment/request/cancel_payment_request.py
shared/payment/request/create_payment_session_request.py
shared/payment/request/query_payment_request.py
shared/payment/service/__init__.py
shared/payment/service/cancel_payment_service.py
shared/payment/service/create_payment_session_service.py
shared/payment/service/query_payment_service.py
shared/refund/__init__.py
shared/refund/request/__init__.py
shared/refund/request/create_refund_request.py
shared/refund/request/query_refund_request.py
shared/refund/service/__init__.py
shared/refund/service/create_refund_service.py
shared/refund/service/query_refund_service.py
ant_intl_antom_mcp-1.0.1.dist-info/METADATA
ant_intl_antom_mcp-1.0.1.dist-info/WHEEL
ant_intl_antom_mcp-1.0.1.dist-info/entry_points.txt
ant_intl_antom_mcp-1.0.1.dist-info/licenses/LICENSE
ant_intl_antom_mcp-1.0.1.dist-info/RECORD
