Metadata-Version: 2.4
Name: ant-intl-antom-mcp
Version: 1.0.1
Summary: A Model Context Protocol (MCP) compatible server that integrates Ant International's Antom payment APIs, enabling AI assistants to handle payment and refund operations seamlessly.
Project-URL: Homepage, https://github.com/alipay/global-antom-mcp
Project-URL: Repository, https://github.com/alipay/global-antom-mcp
Author-email: quding <niuli.nl@ant-intl.com>, lingqi <lilingwei.llw@ant-intl.com>
License: MIT License
License-File: LICENSE
Classifier: Development Status :: 5 - Production/Stable
Classifier: Intended Audience :: Developers
Classifier: License :: OSI Approved :: MIT License
Classifier: Operating System :: OS Independent
Classifier: Programming Language :: Python :: 3.11
Classifier: Programming Language :: Python :: 3.12
Classifier: Topic :: Office/Business :: Financial
Classifier: Topic :: Software Development :: Libraries :: Python Modules
Requires-Python: >=3.11
Requires-Dist: cryptography==44.0.3
Requires-Dist: global-open-sdk-python>=1.4.6
Requires-Dist: mcp[cli]>=1.11.0
Requires-Dist: rsa>=4.9.1
Provides-Extra: dev
Requires-Dist: python-dotenv>=1.1.0; extra == 'dev'
Requires-Dist: twine; extra == 'dev'
